reversecoin-0.0.7.dist-info/METADATA
reversecoin-0.0.7.dist-info/entry_points.txt
reversecoin-0.0.7.dist-info/RECORD
reversecoin-0.0.7.dist-info/WHEEL
reversecoin-0.0.7.dist-info/top_level.txt
reversecoin-0.0.7.dist-info/DESCRIPTION.rst
reversecoin-0.0.7.dist-info/metadata.json
reversecoin/walletdb.py
reversecoin/rpc.py
reversecoin/peermanager.py
reversecoin/connection.py
reversecoin/__init__.py
reversecoin/common.py
reversecoin/mkbootstrap.py
reversecoin/version.py
reversecoin/mempool.py
reversecoin/exceptions.py
reversecoin/transaction.py
reversecoin/utils.py
reversecoin/chaindb.py
reversecoin/vaultdb.py
reversecoin/reversecoinpy.py
reversecoin/cache.py
reversecoin/node.py
reversecoin/bitcoin/core.py
reversecoin/bitcoin/key.py
reversecoin/bitcoin/serialize.py
reversecoin/bitcoin/base58.py
reversecoin/bitcoin/bignum.py
reversecoin/bitcoin/script.py
reversecoin/bitcoin/rpc.py
reversecoin/bitcoin/__init__.py
reversecoin/bitcoin/hash.py
reversecoin/bitcoin/utils.py
reversecoin/bitcoin/bloom.py
reversecoin/bitcoin/messages.py
reversecoin/bitcoin/scripteval.py
reversecoin/bitcoin/coredefs.py
reversecoin/miner/__init__.py
reversecoin/miner/miner.py
reversecoin/data/genesis.dat
reversecoin/bitcoinrpc/data.py
reversecoin/bitcoinrpc/connection.py
reversecoin/bitcoinrpc/__init__.py
reversecoin/bitcoinrpc/util.py
reversecoin/bitcoinrpc/proxy.py
reversecoin/bitcoinrpc/exceptions.py
reversecoin/bitcoinrpc/config.py
reversecoin/wallet/vault_withdraw.py
reversecoin/wallet/blockchain.py
reversecoin/wallet/balance.py
reversecoin/wallet/vault_override.py
reversecoin/wallet/send.py
reversecoin/wallet/wallet.py
reversecoin/wallet/vault_pending.py
reversecoin/wallet/p2sh_send.py
reversecoin/wallet/data.py
reversecoin/wallet/connection.py
reversecoin/wallet/__init__.py
reversecoin/wallet/savings.py
reversecoin/wallet/vault_new.py
reversecoin/wallet/newaddress.py
reversecoin/wallet/sample.py
reversecoin/wallet/getvaults.py
reversecoin/wallet/vault_fast_withdraw.py
reversecoin/wallet/proxy.py
reversecoin/wallet/rwallet.py
reversecoin/wallet/mempool.py
reversecoin/wallet/received.py
reversecoin/wallet/exceptions.py
reversecoin/wallet/config.py
reversecoin/wallet/account.py
