Metadata-Version: 2.0
Name: reversecoin
Version: 0.0.7
Summary: A secure reversable crypto currency
Home-page: http://www.reversecoin.org
Author: Obulpathi N Challa
Author-email: obulpathi@gmail.com
License: UNKNOWN
Platform: UNKNOWN
Requires-Dist: gevent
Requires-Dist: leveldb
